{
  "1486565478505": {
    "✔ ID": "2.1.3",
    "№ Unit": "Unit 2",
    "✔ Unit Name": "Present simple (I do)",
    "✔ ♞ Exercise": "Complete the sentences using the following verbs:",
    "✔ ☛ Question": "Bad driving [[causes]] many accidents.",
    "✎ Choices": "cause(s); close(s); connect(s); go(es); live(s); speak(s); take(s)",
    "♟ Example": "![](18331.png)",
    "♨ Hint Front Image (XXL)": "![](25812.png)",
    "♨ Hint Back Image (XXL)": "![](25812.png)",
    "Tag": "Present_and_past"
  }
}
